prettype/gui.py
prettype/prettype.py
prettype/fonts/Calligraphy-Bold.json
prettype/fonts/Calligraphy-Normal.json
prettype/fonts/Circled.json
prettype/fonts/Double-Struck.json
prettype/fonts/Fraktur-Bold.json
prettype/fonts/Fraktur-Normal.json
prettype/fonts/Inverse-Circled.json
prettype/fonts/Inverse-Squared.json
prettype/fonts/Monospace.json
prettype/fonts/Paranthesized.json
prettype/fonts/Sans-Serif-Bold-Italic.json
prettype/fonts/Sans-Serif-Bold.json
prettype/fonts/Sans-Serif-Italic.json
prettype/fonts/Sans-Serif-Normal.json
prettype/fonts/Serif-Bold-Italic.json
prettype/fonts/Serif-Bold.json
prettype/fonts/Serif-Italic.json
prettype/fonts/Serif-Normal.json
prettype/fonts/Squared.json
prettype-1.0.0.dist-info/METADATA
prettype-1.0.0.dist-info/RECORD
prettype-1.0.0.dist-info/WHEEL
prettype-1.0.0.dist-info/entry_points.txt
prettype-1.0.0.dist-info/top_level.txt
