Metadata-Version: 2.1
Name: prettype
Version: 1.0.0
Summary: An easy to use text stylizer for your desktop!
Home-page: https://github.com/nikhilkumarsingh/prettype
Author: Nikhil Kumar Singh
Author-email: nikhilksingh97@gmail.com
License: MIT
Keywords: unicode styled text keyboard typing tkinter copy paste
Platform: UNKNOWN
Classifier: Development Status :: 4 - Beta
Classifier: License :: OSI Approved :: MIT License
Classifier: Programming Language :: Python
Classifier: Programming Language :: Python :: 3
Classifier: Programming Language :: Python :: 3.1
Classifier: Programming Language :: Python :: 3.2
Classifier: Programming Language :: Python :: 3.3
Classifier: Programming Language :: Python :: 3.4
Classifier: Programming Language :: Python :: 3.5
Classifier: Programming Language :: Python :: 3.6
Classifier: Programming Language :: Python :: 3.7
Requires-Dist: xerox
Requires-Dist: pynput
